{
  "id": "tor",
  "symbol": "tor",
  "name": "TOR",
  "web_slug": "tor",
  "asset_platform_id": "fantom",
  "platforms": {
    "fantom": "0x74e23df9110aa9ea0b6ff2faee01e740ca1c642e",
    "binance-smart-chain": "0x1d6cbdc6b29c6afbae65444a1f65ba9252b8ca83"
  },
  "detail_platforms": {
    "fantom": {
      "decimal_place": 18,
      "contract_address": "0x74e23df9110aa9ea0b6ff2faee01e740ca1c642e",
      "geckoterminal_url": "https://www.geckoterminal.com/ftm/tokens/0x74e23df9110aa9ea0b6ff2faee01e740ca1c642e"
    },
    "binance-smart-chain": {
      "decimal_place": 18,
      "contract_address": "0x1d6cbdc6b29c6afbae65444a1f65ba9252b8ca83",
      "geckoterminal_url": "https://www.geckoterminal.com/bsc/tokens/0x1d6cbdc6b29c6afbae65444a1f65ba9252b8ca83"
    }
  },
  "block_time_in_minutes": 0,
  "hashing_algorithm": null,
  "categories": [
    "Stablecoins",
    "USD Stablecoin",
    "Yield Farming",
    "BNB Chain Ecosystem",
    "Fantom Ecosystem",
    "Fiat-backed Stablecoin"
  ],
  "preview_listing": false,
  "public_notice": null,
  "additional_notices": [
    "Kindly be aware of <a href='https://www.coingecko.com/en/glossary/rug-pulled' target='_blank'>liquidity-related risks</a>. This notice is not directed at any project in particular, and is more of a cautionary reminder."
  ],
  "localization": {
    "en": "TOR",
    "zh": "",
    "zh-tw": "",
    "de": "",
    "fr": "",
    "es": "",
    "ja": "",
    "id": "",
    "ru": "",
    "ko": "",
    "ar": "",
    "th": "",
    "vi": "",
    "it": "",
    "pl": "",
    "tr": "",
    "hu": "",
    "nl": "",
    "ro": "",
    "sv": "",
    "cs": "",
    "da": "",
    "el": "",
    "hi": "",
    "no": "",
    "sk": "",
    "uk": "",
    "he": "",
    "fi": "",
    "bg": "",
    "hr": "",
    "lt": "",
    "sl": "",
    "pt": ""
  },
  "description": {
    "en": "TOR is a truly Fully Collateralised stable coin built on the Fantom Opera Chain. It has a dynamic supply which is determined by supply and demand which ensures it is always worth $1.",
    "zh": "",
    "zh-tw": "",
    "de": "",
    "fr": "",
    "es": "",
    "ja": "",
    "id": "",
    "ru": "",
    "ko": "",
    "ar": "",
    "th": "",
    "vi": "",
    "it": "",
    "pl": "",
    "tr": "",
    "hu": "",
    "nl": "",
    "ro": "",
    "sv": "",
    "cs": "",
    "da": "",
    "el": "",
    "hi": "",
    "no": "",
    "sk": "",
    "uk": "",
    "he": "",
    "fi": "",
    "bg": "",
    "hr": "",
    "lt": "",
    "sl": "",
    "pt": ""
  },
  "links": {
    "homepage": [
      "https://tor.cash/",
      "https://linktr.ee/HectorDAO",
      "https://app.hector.finance/"
    ],
    "whitepaper": "https://docs.hector.finance/whitepaper-and-roadmap/whitepaper",
    "blockchain_site": [
      "https://ftmscan.com/token/0x74e23df9110aa9ea0b6ff2faee01e740ca1c642e",
      "https://platform.arkhamintelligence.com/explorer/token/tor",
      "https://bscscan.com/token/0x1d6cbdc6b29c6afbae65444a1f65ba9252b8ca83",
      "https://binplorer.com/address/0x1d6cbdc6b29c6afbae65444a1f65ba9252b8ca83"
    ],
    "official_forum_url": [
      "https://www.tiktok.com/@hector_network"
    ],
    "chat_url": [
      "https://discord.com/invite/hector",
      "https://instagram.com/hector_network",
      "https://www.youtube.com/c/HectorDAO"
    ],
    "announcement_url": [
      "https://medium.com/@Hector_Network"
    ],
    "snapshot_url": null,
    "twitter_screen_name": "Hector_Network",
    "facebook_username": "",
    "bitcointalk_thread_identifier": null,
    "telegram_channel_identifier": "Hector_Network",
    "subreddit_url": "https://www.reddit.com/r/hectordao/",
    "repos_url": {
      "github": [],
      "bitbucket": []
    }
  },
  "image": {
    "thumb": "https://coin-images.coingecko.com/coins/images/23609/thumb/tor.png?1696522816",
    "small": "https://coin-images.coingecko.com/coins/images/23609/small/tor.png?1696522816",
    "large": "https://coin-images.coingecko.com/coins/images/23609/large/tor.png?1696522816"
  },
  "country_origin": "",
  "genesis_date": null,
  "contract_address": "0x74e23df9110aa9ea0b6ff2faee01e740ca1c642e",
  "sentiment_votes_up_percentage": 0.0,
  "sentiment_votes_down_percentage": 100.0,
  "watchlist_portfolio_users": 15840,
  "market_cap_rank": 5833,
  "market_data": {
    "current_price": {
      "aed": 0.060084,
      "ars": 21.13,
      "aud": 0.02538929,
      "bch": 2.957e-05,
      "bdt": 1.99,
      "bhd": 0.00616756,
      "bmd": 0.01636049,
      "bnb": 1.959e-05,
      "brl": 0.089982,
      "btc": 1.44005e-07,
      "cad": 0.02269219,
      "chf": 0.01322706,
      "clp": 15.76,
      "cny": 0.117552,
      "czk": 0.343924,
      "dkk": 0.10497,
      "dot": 0.00432912,
      "eos": 0.03347269,
      "eth": 3.92e-06,
      "eur": 0.01406197,
      "gbp": 0.01214176,
      "gel": 0.04409152,
      "hkd": 0.127702,
      "huf": 5.54,
      "idr": 266.36,
      "ils": 0.05549,
      "inr": 1.42,
      "jpy": 2.41,
      "krw": 22.89,
      "kwd": 0.00500238,
      "lkr": 4.94,
      "ltc": 0.00014332,
      "mmk": 34.34,
      "mxn": 0.308033,
      "myr": 0.069164,
      "ngn": 25.11,
      "nok": 0.168461,
      "nzd": 0.02807383,
      "php": 0.93609,
      "pkr": 4.63,
      "pln": 0.059768,
      "rub": 1.32,
      "sar": 0.061396,
      "sek": 0.157261,
      "sgd": 0.02103697,
      "sol": 9.056e-05,
      "thb": 0.533025,
      "try": 0.669205,
      "twd": 0.495007,
      "uah": 0.677155,
      "usd": 0.01636049,
      "vef": 0.00163818,
      "vnd": 430.82,
      "xag": 0.00043984,
      "xau": 4.93e-06,
      "xdr": 0.01140531,
      "xlm": 0.04109868,
      "xrp": 0.00564516,
      "yfi": 3e-06,
      "zar": 0.289703,
      "bits": 0.144005,
      "link": 0.00066879,
      "sats": 14.4
    },
    "total_value_locked": null,
    "mcap_to_tvl_ratio": null,
    "fdv_to_tvl_ratio": null,
    "roi": null,
    "ath": {
      "aed": 73.99,
      "ars": 16933.4,
      "aud": 30.75,
      "bch": 0.06729598,
      "bdt": 2211.08,
      "bhd": 7.59,
      "bmd": 20.14,
      "bnb": 0.050559,
      "brl": 100.32,
      "btc": 0.00035679,
      "cad": 27.19,
      "chf": 17.74,
      "clp": 19944.43,
      "cny": 145.01,
      "czk": 470.54,
      "dkk": 138.44,
      "dot": 2.480962,
      "eos": 24.415716,
      "eth": 0.0062069,
      "eur": 18.57,
      "gbp": 15.89,
      "gel": 53.38,
      "hkd": 157.61,
      "huf": 7225.25,
      "idr": 315305,
      "ils": 73.03,
      "inr": 1669.88,
      "jpy": 3026.88,
      "krw": 26817,
      "kwd": 6.2,
      "lkr": 6261.76,
      "ltc": 0.26668672,
      "mmk": 42311,
      "mxn": 343.62,
      "myr": 96.0,
      "ngn": 31717,
      "nok": 211.95,
      "nzd": 32.68,
      "php": 1130.75,
      "pkr": 5626.47,
      "pln": 79.98,
      "rub": 1849.0,
      "sar": 75.55,
      "sek": 207.43,
      "sgd": 27.07,
      "sol": 0.00737361,
      "thb": 721.92,
      "try": 627.31,
      "twd": 636.68,
      "uah": 773.8,
      "usd": 20.14,
      "vef": 2.02,
      "vnd": 496216,
      "xag": 0.890263,
      "xau": 0.0098981,
      "xdr": 15.18,
      "xlm": 168.109,
      "xrp": 36.316942,
      "yfi": 0.00238033,
      "zar": 386.51,
      "bits": 356.79,
      "link": 1.051147,
      "sats": 35679
    },
    "ath_change_percentage": {
      "aed": -99.91867,
      "ars": -99.87504,
      "aud": -99.91731,
      "bch": -99.95588,
      "bdt": -99.90995,
      "bhd": -99.91866,
      "bmd": -99.91867,
      "bnb": -99.96127,
      "brl": -99.91014,
      "btc": -99.95954,
      "cad": -99.9164,
      "chf": -99.92533,
      "clp": -99.92085,
      "cny": -99.91882,
      "czk": -99.92681,
      "dkk": -99.92408,
      "dot": -99.82517,
      "eos": -99.8625,
      "eth": -99.93656,
      "eur": -99.92419,
      "gbp": -99.9235,
      "gel": -99.91728,
      "hkd": -99.91884,
      "huf": -99.92325,
      "idr": -99.91538,
      "ils": -99.92391,
      "inr": -99.91462,
      "jpy": -99.92014,
      "krw": -99.91448,
      "kwd": -99.91918,
      "lkr": -99.92105,
      "ltc": -99.94623,
      "mmk": -99.91872,
      "mxn": -99.91024,
      "myr": -99.92785,
      "ngn": -99.92073,
      "nok": -99.92041,
      "nzd": -99.91411,
      "php": -99.91713,
      "pkr": -99.91757,
      "pln": -99.92517,
      "rub": -99.92843,
      "sar": -99.91862,
      "sek": -99.92409,
      "sgd": -99.92216,
      "sol": -98.77218,
      "thb": -99.92605,
      "try": -99.89317,
      "twd": -99.92208,
      "uah": -99.91236,
      "usd": -99.91867,
      "vef": -99.91867,
      "vnd": -99.91307,
      "xag": -99.95056,
      "xau": -99.95015,
      "xdr": -99.92477,
      "xlm": -99.9755,
      "xrp": -99.98442,
      "yfi": -99.8736,
      "zar": -99.92495,
      "bits": -99.95954,
      "link": -99.93602,
      "sats": -99.95954
    },
    "ath_date": {
      "aed": "2024-02-27T10:24:31.893Z",
      "ars": "2024-02-27T10:24:31.893Z",
      "aud": "2024-02-27T10:24:31.893Z",
      "bch": "2024-02-27T09:04:37.835Z",
      "bdt": "2024-02-27T10:24:31.893Z",
      "bhd": "2024-02-27T10:24:31.893Z",
      "bmd": "2024-02-27T10:24:31.893Z",
      "bnb": "2024-02-27T10:34:35.731Z",
      "brl": "2024-02-27T10:24:31.893Z",
      "btc": "2024-02-27T07:50:06.349Z",
      "cad": "2024-02-27T10:24:31.893Z",
      "chf": "2024-02-27T10:29:34.068Z",
      "clp": "2024-02-27T10:24:31.893Z",
      "cny": "2024-02-27T10:24:31.893Z",
      "czk": "2024-02-27T10:29:34.068Z",
      "dkk": "2024-02-27T10:24:31.893Z",
      "dot": "2024-02-27T07:59:42.215Z",
      "eos": "2024-02-27T07:55:12.205Z",
      "eth": "2024-02-27T07:50:06.349Z",
      "eur": "2024-02-27T10:24:31.893Z",
      "gbp": "2024-02-27T10:24:31.893Z",
      "gel": "2024-02-27T10:24:31.893Z",
      "hkd": "2024-02-27T10:24:31.893Z",
      "huf": "2024-02-27T10:24:31.893Z",
      "idr": "2024-02-27T10:29:34.068Z",
      "ils": "2024-02-27T10:24:31.893Z",
      "inr": "2024-02-27T10:24:31.893Z",
      "jpy": "2024-02-27T10:24:31.893Z",
      "krw": "2024-02-27T10:24:31.893Z",
      "kwd": "2024-02-27T10:24:31.893Z",
      "lkr": "2024-02-27T10:24:31.893Z",
      "ltc": "2024-02-27T10:20:24.071Z",
      "mmk": "2024-02-27T10:24:31.893Z",
      "mxn": "2024-02-27T10:24:31.893Z",
      "myr": "2024-02-27T10:24:31.893Z",
      "ngn": "2024-02-27T10:24:31.893Z",
      "nok": "2024-02-27T10:29:34.068Z",
      "nzd": "2024-02-27T10:24:31.893Z",
      "php": "2024-02-27T10:24:31.893Z",
      "pkr": "2024-02-27T10:24:31.893Z",
      "pln": "2024-02-27T10:29:34.068Z",
      "rub": "2024-02-27T09:45:27.533Z",
      "sar": "2024-02-27T10:24:31.893Z",
      "sek": "2024-02-27T10:29:34.068Z",
      "sgd": "2024-02-27T10:24:31.893Z",
      "sol": "2025-08-18T09:31:22.648Z",
      "thb": "2024-02-27T10:24:31.893Z",
      "try": "2024-02-27T10:24:31.893Z",
      "twd": "2024-02-27T10:24:31.893Z",
      "uah": "2024-02-27T10:24:31.893Z",
      "usd": "2024-02-27T10:24:31.893Z",
      "vef": "2024-02-27T10:24:31.893Z",
      "vnd": "2024-02-27T10:24:31.893Z",
      "xag": "2024-02-27T10:29:34.068Z",
      "xau": "2024-02-27T10:24:31.893Z",
      "xdr": "2024-02-27T10:24:31.893Z",
      "xlm": "2024-02-27T07:50:06.349Z",
      "xrp": "2024-02-27T07:50:06.349Z",
      "yfi": "2024-02-27T10:29:34.068Z",
      "zar": "2024-02-27T10:24:31.893Z",
      "bits": "2024-02-27T07:50:06.349Z",
      "link": "2024-02-27T07:55:12.205Z",
      "sats": "2024-02-27T07:50:06.349Z"
    },
    "atl": {
      "aed": 0.0036611,
      "ars": 0.355901,
      "aud": 0.00151889,
      "bch": 3.12e-06,
      "bdt": 0.110042,
      "bhd": 0.00037576,
      "bmd": 0.00099689,
      "bnb": 2.33e-06,
      "brl": 0.00488875,
      "btc": 1.5593e-08,
      "cad": 0.00136605,
      "chf": 0.0008812,
      "clp": 0.870713,
      "cny": 0.00707968,
      "czk": 0.02228603,
      "dkk": 0.0068153,
      "dot": 0.00019149,
      "eos": 0.0014721,
      "eth": 4.39008e-07,
      "eur": 0.00091419,
      "gbp": 0.00079499,
      "gel": 0.00485082,
      "hkd": 0.0077718,
      "huf": 0.346979,
      "idr": 15.51,
      "ils": 0.00373406,
      "inr": 0.083087,
      "jpy": 0.148811,
      "krw": 1.3,
      "kwd": 0.00030733,
      "lkr": 0.328121,
      "ltc": 1.43e-05,
      "mmk": 2.1,
      "mxn": 0.01712583,
      "myr": 0.00467043,
      "ngn": 0.802855,
      "nok": 0.01073919,
      "nzd": 0.0016464,
      "php": 0.055213,
      "pkr": 0.281457,
      "pln": 0.00399961,
      "rub": 0.087987,
      "sar": 0.00373851,
      "sek": 0.01046484,
      "sgd": 0.00133687,
      "sol": 1.032e-05,
      "thb": 0.03531191,
      "try": 0.02878186,
      "twd": 0.03151637,
      "uah": 0.03593422,
      "usd": 0.00099689,
      "vef": 9.982e-05,
      "vnd": 24.2,
      "xag": 4.201e-05,
      "xau": 4.99991e-07,
      "xdr": 0.00074974,
      "xlm": 0.00415996,
      "xrp": 0.00058019,
      "yfi": 1.13055e-07,
      "zar": 0.0187511,
      "bits": 0.01559332,
      "link": 6.898e-05,
      "sats": 1.56
    },
    "atl_change_percentage": {
      "aed": 1543.4989,
      "ars": 5845.44172,
      "aud": 1574.10854,
      "bch": 850.57806,
      "bdt": 1709.32402,
      "bhd": 1543.79786,
      "bmd": 1543.51009,
      "bnb": 741.74577,
      "brl": 1743.88661,
      "btc": 825.73329,
      "cad": 1563.68599,
      "chf": 1402.77214,
      "clp": 1713.06769,
      "cny": 1562.77143,
      "czk": 1445.2206,
      "dkk": 1442.21464,
      "dot": 2165.13237,
      "eos": 2180.5193,
      "eth": 796.89553,
      "eur": 1440.03079,
      "gbp": 1429.19583,
      "gel": 810.25558,
      "hkd": 1545.95637,
      "huf": 1498.12665,
      "idr": 1619.9844,
      "ils": 1388.18116,
      "inr": 1616.02944,
      "jpy": 1524.33353,
      "krw": 1664.32499,
      "kwd": 1529.94234,
      "lkr": 1406.73243,
      "ltc": 902.72685,
      "mmk": 1540.7701,
      "mxn": 1701.0051,
      "myr": 1383.01791,
      "ngn": 3031.4973,
      "nok": 1470.82976,
      "nzd": 1605.13179,
      "php": 1597.12806,
      "pkr": 1547.72439,
      "pln": 1396.29483,
      "rub": 1404.10258,
      "sar": 1544.55794,
      "sek": 1404.61315,
      "sgd": 1475.87121,
      "sol": 777.3842,
      "thb": 1411.87509,
      "try": 2228.4868,
      "twd": 1474.09881,
      "uah": 1787.13509,
      "usd": 1543.51009,
      "vef": 1543.51009,
      "vnd": 1682.93847,
      "xag": 947.78557,
      "xau": 886.82532,
      "xdr": 1423.42173,
      "xlm": 890.21721,
      "xrp": 875.49323,
      "yfi": 2561.32827,
      "zar": 1446.90685,
      "bits": 825.73329,
      "link": 875.00788,
      "sats": 825.73329
    },
    "atl_date": {
      "aed": "2023-11-24T04:10:55.233Z",
      "ars": "2023-11-24T04:10:55.233Z",
      "aud": "2023-11-24T05:11:40.131Z",
      "bch": "2025-08-07T07:20:22.050Z",
      "bdt": "2023-11-24T04:10:55.233Z",
      "bhd": "2023-11-24T04:10:55.233Z",
      "bmd": "2023-11-24T04:10:55.233Z",
      "bnb": "2025-08-06T21:19:43.149Z",
      "brl": "2023-11-24T04:10:55.233Z",
      "btc": "2025-08-06T21:19:43.149Z",
      "cad": "2023-11-24T05:11:40.131Z",
      "chf": "2023-11-24T05:11:40.131Z",
      "clp": "2023-11-24T04:10:55.233Z",
      "cny": "2023-11-24T05:11:40.131Z",
      "czk": "2023-11-24T05:11:40.131Z",
      "dkk": "2023-11-24T05:11:40.131Z",
      "dot": "2023-11-24T08:11:40.539Z",
      "eos": "2023-11-24T03:30:41.358Z",
      "eth": "2025-08-13T01:56:30.083Z",
      "eur": "2023-11-24T05:11:40.131Z",
      "gbp": "2023-11-24T05:11:40.131Z",
      "gel": "2025-08-06T21:40:33.872Z",
      "hkd": "2023-11-24T04:10:55.233Z",
      "huf": "2023-11-24T05:11:40.131Z",
      "idr": "2023-11-24T05:11:40.131Z",
      "ils": "2023-11-24T07:11:34.088Z",
      "inr": "2023-11-24T04:10:55.233Z",
      "jpy": "2023-11-24T05:11:40.131Z",
      "krw": "2023-11-24T05:11:40.131Z",
      "kwd": "2023-11-24T04:10:55.233Z",
      "lkr": "2023-11-24T04:10:55.233Z",
      "ltc": "2023-11-24T10:20:29.455Z",
      "mmk": "2023-11-24T04:10:55.233Z",
      "mxn": "2023-11-24T05:11:40.131Z",
      "myr": "2023-11-24T04:10:55.233Z",
      "ngn": "2023-11-24T04:10:55.233Z",
      "nok": "2023-11-24T05:11:40.131Z",
      "nzd": "2023-11-24T05:11:40.131Z",
      "php": "2023-11-24T05:11:40.131Z",
      "pkr": "2023-11-24T04:10:55.233Z",
      "pln": "2023-11-24T05:11:40.131Z",
      "rub": "2023-11-24T04:10:55.233Z",
      "sar": "2023-11-24T04:10:55.233Z",
      "sek": "2023-11-24T05:11:40.131Z",
      "sgd": "2023-11-24T05:11:40.131Z",
      "sol": "2025-08-13T03:48:36.066Z",
      "thb": "2023-11-24T05:11:40.131Z",
      "try": "2023-11-24T04:15:24.674Z",
      "twd": "2023-11-24T05:11:40.131Z",
      "uah": "2023-11-24T04:10:55.233Z",
      "usd": "2023-11-24T04:10:55.233Z",
      "vef": "2023-11-24T04:10:55.233Z",
      "vnd": "2023-11-24T03:40:57.904Z",
      "xag": "2023-11-24T05:11:40.131Z",
      "xau": "2023-11-24T05:11:40.131Z",
      "xdr": "2023-11-24T04:10:55.233Z",
      "xlm": "2025-08-08T11:31:39.973Z",
      "xrp": "2025-08-08T03:12:14.571Z",
      "yfi": "2023-11-24T10:40:40.358Z",
      "zar": "2023-11-24T07:05:29.510Z",
      "bits": "2025-08-06T21:19:43.149Z",
      "link": "2023-11-24T09:55:30.079Z",
      "sats": "2025-08-06T21:19:43.149Z"
    },
    "market_cap": {
      "aed": 1027126,
      "ars": 361208541,
      "aud": 433942,
      "bch": 505.847,
      "bdt": 33987361,
      "bhd": 105440,
      "bmd": 279680,
      "bnb": 334.809,
      "brl": 1537938,
      "btc": 2.461969,
      "cad": 387931,
      "chf": 226078,
      "clp": 269483058,
      "cny": 2009530,
      "czk": 5879102,
      "dkk": 1794365,
      "dot": 73954,
      "eos": 572690,
      "eth": 67.107,
      "eur": 240377,
      "gbp": 207553,
      "gel": 753738,
      "hkd": 2183761,
      "huf": 94666847,
      "idr": 4553271423,
      "ils": 948591,
      "inr": 24350047,
      "jpy": 41277161,
      "krw": 391358076,
      "kwd": 85509,
      "lkr": 84394072,
      "ltc": 2448,
      "mmk": 587048736,
      "mxn": 5265763,
      "myr": 1182348,
      "ngn": 429172061,
      "nok": 2879758,
      "nzd": 479797,
      "php": 16002321,
      "pkr": 79166019,
      "pln": 1021658,
      "rub": 22591175,
      "sar": 1049519,
      "sek": 2688384,
      "sgd": 359625,
      "sol": 1547,
      "thb": 9114498,
      "try": 11439955,
      "twd": 8464150,
      "uah": 11575867,
      "usd": 279680,
      "vef": 28004,
      "vnd": 7364850637,
      "xag": 7514.51,
      "xau": 84.26,
      "xdr": 194972,
      "xlm": 702519,
      "xrp": 96530,
      "yfi": 51.321,
      "zar": 4952390,
      "bits": 2461969,
      "link": 11449,
      "sats": 246196879
    },
    "market_cap_rank": 5833,
    "fully_diluted_valuation": {
      "aed": 1027126,
      "ars": 361208541,
      "aud": 433942,
      "bch": 505.847,
      "bdt": 33987361,
      "bhd": 105440,
      "bmd": 279680,
      "bnb": 334.809,
      "brl": 1537938,
      "btc": 2.461969,
      "cad": 387931,
      "chf": 226078,
      "clp": 269483058,
      "cny": 2009530,
      "czk": 5879102,
      "dkk": 1794365,
      "dot": 73954,
      "eos": 572690,
      "eth": 67.107,
      "eur": 240377,
      "gbp": 207553,
      "gel": 753738,
      "hkd": 2183761,
      "huf": 94666847,
      "idr": 4553271423,
      "ils": 948591,
      "inr": 24350047,
      "jpy": 41277161,
      "krw": 391358076,
      "kwd": 85509,
      "lkr": 84394072,
      "ltc": 2448,
      "mmk": 587048736,
      "mxn": 5265763,
      "myr": 1182348,
      "ngn": 429172061,
      "nok": 2879758,
      "nzd": 479797,
      "php": 16002321,
      "pkr": 79166019,
      "pln": 1021658,
      "rub": 22591175,
      "sar": 1049519,
      "sek": 2688384,
      "sgd": 359625,
      "sol": 1547,
      "thb": 9114498,
      "try": 11439955,
      "twd": 8464150,
      "uah": 11575867,
      "usd": 279680,
      "vef": 28004,
      "vnd": 7364850637,
      "xag": 7514.51,
      "xau": 84.26,
      "xdr": 194972,
      "xlm": 702519,
      "xrp": 96530,
      "yfi": 51.321,
      "zar": 4952390,
      "bits": 2461969,
      "link": 11449,
      "sats": 246196879
    },
    "market_cap_fdv_ratio": 1.0,
    "total_volume": {
      "aed": 83.32,
      "ars": 29300,
      "aud": 35.21,
      "bch": 0.04100497,
      "bdt": 2756.99,
      "bhd": 8.55,
      "bmd": 22.69,
      "bnb": 0.02715988,
      "brl": 124.78,
      "btc": 0.00019969,
      "cad": 31.47,
      "chf": 18.34,
      "clp": 21860,
      "cny": 163.01,
      "czk": 476.92,
      "dkk": 145.56,
      "dot": 6.003211,
      "eos": 46.416712,
      "eth": 0.00544233,
      "eur": 19.5,
      "gbp": 16.84,
      "gel": 61.14,
      "hkd": 177.09,
      "huf": 7679.56,
      "idr": 369362,
      "ils": 76.95,
      "inr": 1975.31,
      "jpy": 3348.18,
      "krw": 31745,
      "kwd": 6.94,
      "lkr": 6845.9,
      "ltc": 0.19873906,
      "mmk": 47620,
      "mxn": 427.15,
      "myr": 95.91,
      "ngn": 34814,
      "nok": 233.61,
      "nzd": 38.93,
      "php": 1298.08,
      "pkr": 6421.8,
      "pln": 82.88,
      "rub": 1832.58,
      "sar": 85.14,
      "sek": 218.07,
      "sgd": 29.17,
      "sol": 0.12557837,
      "thb": 739.15,
      "try": 927.99,
      "twd": 686.43,
      "uah": 939.01,
      "usd": 22.69,
      "vef": 2.27,
      "vnd": 597423,
      "xag": 0.60993,
      "xau": 0.00683587,
      "xdr": 15.82,
      "xlm": 56.992,
      "xrp": 7.828166,
      "yfi": 0.0041609,
      "zar": 401.73,
      "bits": 199.69,
      "link": 0.92741511,
      "sats": 19969.21
    },
    "high_24h": {
      "aed": 2.31,
      "ars": 814.57,
      "aud": 0.972343,
      "bch": 0.00111667,
      "bdt": 76.53,
      "bhd": 0.237553,
      "bmd": 0.630082,
      "bnb": 0.00075264,
      "brl": 3.43,
      "btc": 5.49e-06,
      "cad": 0.8708,
      "chf": 0.508706,
      "clp": 607.5,
      "cny": 4.53,
      "czk": 13.23,
      "dkk": 4.03,
      "dot": 0.16512362,
      "eos": 1.288717,
      "eth": 0.00014964,
      "eur": 0.54057,
      "gbp": 0.466777,
      "gel": 1.69,
      "hkd": 4.92,
      "huf": 213.57,
      "idr": 10260.71,
      "ils": 2.13,
      "inr": 55.0,
      "jpy": 93.1,
      "krw": 876.42,
      "kwd": 0.192605,
      "lkr": 189.63,
      "ltc": 0.00552183,
      "mmk": 1322.54,
      "mxn": 11.85,
      "myr": 2.66,
      "ngn": 967.26,
      "nok": 6.44,
      "nzd": 1.065,
      "php": 36.01,
      "pkr": 177.68,
      "pln": 2.3,
      "rub": 50.8,
      "sar": 2.36,
      "sek": 6.03,
      "sgd": 0.80913,
      "sol": 0.00351173,
      "thb": 20.49,
      "try": 25.77,
      "twd": 19.01,
      "uah": 25.97,
      "usd": 0.630082,
      "vef": 0.06309,
      "vnd": 16578.45,
      "xag": 0.01663685,
      "xau": 0.00018887,
      "xdr": 0.439246,
      "xlm": 1.558551,
      "xrp": 0.21019116,
      "yfi": 0.0001157,
      "zar": 11.13,
      "bits": 5.49,
      "link": 0.02620556,
      "sats": 549.29
    },
    "low_24h": {
      "aed": 0.03277499,
      "ars": 11.52,
      "aud": 0.0138282,
      "bch": 1.602e-05,
      "bdt": 1.084,
      "bhd": 0.00336391,
      "bmd": 0.00892322,
      "bnb": 1.071e-05,
      "brl": 0.0491152,
      "btc": 7.8691e-08,
      "cad": 0.01237075,
      "chf": 0.00720673,
      "clp": 8.6,
      "cny": 0.06409,
      "czk": 0.187378,
      "dkk": 0.057197,
      "dot": 0.00236737,
      "eos": 0.01818012,
      "eth": 2.15e-06,
      "eur": 0.00766217,
      "gbp": 0.00661618,
      "gel": 0.02404808,
      "hkd": 0.069598,
      "huf": 3.02,
      "idr": 145.33,
      "ils": 0.03026489,
      "inr": 0.776819,
      "jpy": 1.32,
      "krw": 12.43,
      "kwd": 0.00272769,
      "lkr": 2.69,
      "ltc": 7.839e-05,
      "mmk": 18.73,
      "mxn": 0.167973,
      "myr": 0.03768277,
      "ngn": 13.69,
      "nok": 0.091765,
      "nzd": 0.01513481,
      "php": 0.510435,
      "pkr": 2.52,
      "pln": 0.03251935,
      "rub": 0.720773,
      "sar": 0.03348454,
      "sek": 0.085624,
      "sgd": 0.01146638,
      "sol": 5.012e-05,
      "thb": 0.29087,
      "try": 0.364864,
      "twd": 0.268946,
      "uah": 0.367842,
      "usd": 0.00892322,
      "vef": 0.00089348,
      "vnd": 234.79,
      "xag": 0.00023876,
      "xau": 2.69e-06,
      "xdr": 0.0062206,
      "xlm": 0.02244071,
      "xrp": 0.00305973,
      "yfi": 1.64e-06,
      "zar": 0.157842,
      "bits": 0.078691,
      "link": 0.00037199,
      "sats": 7.87
    },
    "price_change_24h": -0.6136829511288128,
    "price_change_percentage_24h": -97.40328,
    "price_change_percentage_7d": 699.59382,
    "price_change_percentage_14d": -10.5593,
    "price_change_percentage_30d": 544.017,
    "price_change_percentage_60d": -10.8629,
    "price_change_percentage_200d": 267.23109,
    "price_change_percentage_1y": 157.60195,
    "market_cap_change_24h": -10475464.688280039,
    "market_cap_change_percentage_24h": -97.39957,
    "price_change_24h_in_currency": {
      "aed": -2.2537506380205663,
      "ars": -793.3444767672688,
      "aud": -0.9452524870204229,
      "bch": -0.00108071394823501,
      "bdt": -74.5340055294665,
      "bhd": -0.23134747536390982,
      "bmd": -0.6136829511288128,
      "bnb": -0.000723732085124728,
      "brl": -3.3355643124916723,
      "btc": -5.319870879461e-06,
      "cad": -0.84728879873259,
      "chf": -0.49527721756227194,
      "clp": -591.6986976636657,
      "cny": -4.407357233146556,
      "czk": -12.872434583666372,
      "dkk": -3.9269933123734155,
      "dot": -0.159814507678996,
      "eos": -1.2466156987072479,
      "eth": -0.000144963289519623,
      "eur": -0.5261227833874648,
      "gbp": -0.45430901382270156,
      "gel": -1.6507253360904637,
      "hkd": -4.782684831039176,
      "huf": -207.91917833948983,
      "idr": -9962.423165106873,
      "ils": -2.0716155387603394,
      "inr": -53.57196175445757,
      "jpy": -90.68503337401648,
      "krw": -851.9861928579542,
      "kwd": -0.18758488535783654,
      "lkr": -184.6838934968693,
      "ltc": -0.005248352082829224,
      "mmk": -1288.1205144193784,
      "mxn": -11.530478055997035,
      "myr": -2.5943446758970574,
      "ngn": -940.681954963328,
      "nok": -6.260847778283192,
      "nzd": -1.0349562534318482,
      "php": -35.03266925812237,
      "pkr": -173.04126520049564,
      "pln": -2.234113696994649,
      "rub": -49.396553925566806,
      "sar": -2.3028550118940663,
      "sek": -5.870534511239106,
      "sgd": -0.7877233310926565,
      "sol": -0.003412505359826277,
      "thb": -19.94199341645971,
      "try": -25.0889634795495,
      "twd": -18.461928364243033,
      "uah": -25.295133264854304,
      "usd": -0.6136829511288128,
      "vef": -0.06144807389652806,
      "vnd": -16138.367406061932,
      "xag": -0.016174744463495223,
      "xau": -0.000183799933549629,
      "xdr": -0.4278137273056739,
      "xlm": -1.503157644487516,
      "xrp": -0.20414621610222303,
      "yfi": -0.000112226113173821,
      "zar": -10.828374121943773,
      "bits": -5.31987087946067,
      "link": -0.025480982914015612,
      "sats": -531.9870879460672
    },
    "price_change_percentage_1h_in_currency": {
      "aed": -0.47315,
      "ars": -0.47536,
      "aud": -0.64415,
      "bch": -0.88431,
      "bdt": -0.47315,
      "bhd": -0.47658,
      "bmd": -0.47315,
      "bnb": -0.36919,
      "brl": -0.46681,
      "btc": -0.54353,
      "cad": -0.50665,
      "chf": -0.46711,
      "clp": -0.47315,
      "cny": -0.47869,
      "czk": -0.48704,
      "dkk": -0.48528,
      "dot": -1.17307,
      "eos": -0.70891,
      "eth": -1.12903,
      "eur": -0.4853,
      "gbp": -0.48803,
      "gel": -0.47315,
      "hkd": -0.46958,
      "huf": -0.49641,
      "idr": -0.47192,
      "ils": -0.47315,
      "inr": -0.53278,
      "jpy": -0.43902,
      "krw": -0.50495,
      "kwd": -0.46306,
      "lkr": -0.47315,
      "ltc": -0.86235,
      "mmk": -0.47315,
      "mxn": -0.50757,
      "myr": -0.43782,
      "ngn": -0.47315,
      "nok": -0.50131,
      "nzd": -0.47297,
      "php": -0.4192,
      "pkr": -0.47315,
      "pln": -0.48862,
      "rub": -0.47194,
      "sar": -0.47047,
      "sek": -0.50305,
      "sgd": -0.48042,
      "sol": -0.53412,
      "thb": -0.49758,
      "try": -0.47362,
      "twd": -0.59142,
      "uah": -0.47315,
      "usd": -0.47315,
      "vef": -0.47315,
      "vnd": -0.40763,
      "xag": -0.43963,
      "xau": -0.50947,
      "xdr": -0.47315,
      "xlm": -0.97355,
      "xrp": -0.82144,
      "yfi": -1.20878,
      "zar": -0.55733,
      "bits": -0.54353,
      "link": -2.29109,
      "sats": -0.54353
    },
    "price_change_percentage_24h_in_currency": {
      "aed": -97.40328,
      "ars": -97.40579,
      "aud": -97.38428,
      "bch": -97.33671,
      "bdt": -97.40185,
      "bhd": -97.4033,
      "bmd": -97.40328,
      "bnb": -97.36507,
      "brl": -97.37321,
      "btc": -97.36442,
      "cad": -97.39164,
      "chf": -97.39883,
      "clp": -97.40495,
      "cny": -97.40212,
      "czk": -97.39774,
      "dkk": -97.39656,
      "dot": -97.3626,
      "eos": -97.38513,
      "eth": -97.36402,
      "eur": -97.39682,
      "gbp": -97.39699,
      "gel": -97.39845,
      "hkd": -97.39934,
      "huf": -97.40557,
      "idr": -97.39598,
      "ils": -97.3913,
      "inr": -97.40989,
      "jpy": -97.40655,
      "krw": -97.38338,
      "kwd": -97.40254,
      "lkr": -97.39648,
      "ltc": -97.34187,
      "mmk": -97.40328,
      "mxn": -97.39804,
      "myr": -97.40328,
      "ngn": -97.40053,
      "nok": -97.3798,
      "nzd": -97.35907,
      "php": -97.39749,
      "pkr": -97.39352,
      "pln": -97.39446,
      "rub": -97.39435,
      "sar": -97.40317,
      "sek": -97.39107,
      "sgd": -97.39886,
      "sol": -97.41487,
      "thb": -97.39671,
      "try": -97.40197,
      "twd": -97.38878,
      "uah": -97.39278,
      "usd": -97.40328,
      "vef": -97.40328,
      "vnd": -97.39986,
      "xag": -97.35268,
      "xau": -97.38802,
      "xdr": -97.40328,
      "xlm": -97.33861,
      "xrp": -97.30916,
      "yfi": -97.39594,
      "zar": -97.3943,
      "bits": -97.36442,
      "link": -97.44246,
      "sats": -97.36442
    },
    "price_change_percentage_7d_in_currency": {
      "aed": 699.48498,
      "ars": 684.24,
      "aud": 710.47878,
      "bch": 791.35132,
      "bdt": 698.79581,
      "bhd": 699.4475,
      "bmd": 699.59382,
      "bnb": 700.05889,
      "brl": 713.98672,
      "btc": 741.31084,
      "cad": 705.16082,
      "chf": 701.59067,
      "clp": 705.18434,
      "cny": 699.89441,
      "czk": 702.55063,
      "dkk": 703.34206,
      "dot": 781.16907,
      "eos": 797.68869,
      "eth": 785.69587,
      "eur": 703.11366,
      "gbp": 701.34631,
      "gel": 699.59382,
      "hkd": 695.07124,
      "huf": 699.59252,
      "idr": 701.38604,
      "ils": 693.17908,
      "inr": 695.03455,
      "jpy": 697.11893,
      "krw": 709.19905,
      "kwd": 700.35554,
      "lkr": 701.21496,
      "ltc": 818.01432,
      "mmk": 699.59382,
      "mxn": 710.15151,
      "myr": 700.54065,
      "ngn": 699.59904,
      "nok": 706.25762,
      "nzd": 717.90862,
      "php": 703.65296,
      "pkr": 697.18445,
      "pln": 702.12919,
      "rub": 712.939,
      "sar": 699.50136,
      "sek": 705.53588,
      "sgd": 701.57057,
      "sol": 775.36289,
      "thb": 705.25383,
      "try": 702.46594,
      "twd": 707.63784,
      "uah": 697.5104,
      "usd": 699.59382,
      "vef": 699.59382,
      "vnd": 701.6994,
      "xag": 719.97145,
      "xau": 707.96008,
      "xdr": 693.66009,
      "xlm": 793.89939,
      "xrp": 792.21023,
      "yfi": 763.96512,
      "zar": 704.96211,
      "bits": 741.31084,
      "link": 687.36287,
      "sats": 741.31084
    },
    "price_change_percentage_14d_in_currency": {
      "aed": -10.5593,
      "ars": -15.28376,
      "aud": -10.1179,
      "bch": -10.96548,
      "bdt": -9.97016,
      "bhd": -10.55455,
      "bmd": -10.5593,
      "bnb": -19.40631,
      "brl": -11.69681,
      "btc": -10.04516,
      "cad": -9.98305,
      "chf": -10.41891,
      "clp": -11.23491,
      "cny": -10.48829,
      "czk": -11.55401,
      "dkk": -11.06089,
      "dot": -14.34113,
      "eos": -8.94529,
      "eth": -24.27527,
      "eur": -11.07947,
      "gbp": -11.90154,
      "gel": -10.72493,
      "hkd": -11.06541,
      "huf": -12.18765,
      "idr": -11.1828,
      "ils": -11.32453,
      "inr": -11.00092,
      "jpy": -10.68822,
      "krw": -9.64245,
      "kwd": -10.52594,
      "lkr": -9.29062,
      "ltc": -12.84998,
      "mmk": -10.5593,
      "mxn": -10.69415,
      "myr": -10.75984,
      "ngn": -9.30212,
      "nok": -10.14364,
      "nzd": -9.32715,
      "php": -10.90267,
      "pkr": -9.64719,
      "pln": -11.57879,
      "rub": -9.12372,
      "sar": -10.52577,
      "sek": -11.13806,
      "sgd": -10.70159,
      "sol": -19.98151,
      "thb": -10.37636,
      "try": -10.05337,
      "twd": -9.49303,
      "uah": -10.3218,
      "usd": -10.5593,
      "vef": -10.5593,
      "vnd": -10.01759,
      "xag": -10.55653,
      "xau": -9.56888,
      "xdr": -11.67288,
      "xlm": -8.07293,
      "xrp": -8.22358,
      "yfi": -15.29408,
      "zar": -12.36232,
      "bits": -10.04516,
      "link": -39.72623,
      "sats": -10.04516
    },
    "price_change_percentage_30d_in_currency": {
      "aed": 544.017,
      "ars": 551.81627,
      "aud": 549.93307,
      "bch": 520.45926,
      "bdt": 543.45066,
      "bhd": 542.88804,
      "bmd": 544.017,
      "bnb": 483.46884,
      "brl": 533.27993,
      "btc": 569.19736,
      "cad": 550.54301,
      "chf": 549.3752,
      "clp": 545.35758,
      "cny": 544.67198,
      "czk": 538.63971,
      "dkk": 543.22961,
      "dot": 666.02206,
      "eos": 724.03844,
      "eth": 478.47904,
      "eur": 543.2028,
      "gbp": 540.98627,
      "gel": 540.45233,
      "hkd": 540.42047,
      "huf": 534.89828,
      "idr": 541.62402,
      "ils": 550.50052,
      "inr": 550.86462,
      "jpy": 539.95571,
      "krw": 547.52359,
      "kwd": 544.26985,
      "lkr": 542.92233,
      "ltc": 559.26035,
      "mmk": 544.32396,
      "mxn": 547.52389,
      "myr": 542.19409,
      "ngn": 545.5736,
      "nok": 551.75593,
      "nzd": 556.99492,
      "php": 544.20832,
      "pkr": 538.84021,
      "pln": 544.14765,
      "rub": 561.13162,
      "sar": 544.2874,
      "sek": 539.83541,
      "sgd": 544.56339,
      "sol": 551.96231,
      "thb": 547.34512,
      "try": 552.103,
      "twd": 561.7605,
      "uah": 537.03422,
      "usd": 544.017,
      "vef": 544.017,
      "vnd": 548.59592,
      "xag": 562.14394,
      "xau": 550.68997,
      "xdr": 539.34429,
      "xlm": 677.17133,
      "xrp": 673.06568,
      "yfi": 626.44053,
      "zar": 543.76313,
      "bits": 569.19736,
      "link": 409.70692,
      "sats": 569.19736
    },
    "price_change_percentage_60d_in_currency": {
      "aed": -10.85914,
      "ars": -1.14297,
      "aud": -10.2388,
      "bch": -20.59721,
      "bdt": -11.35163,
      "bhd": -10.93543,
      "bmd": -10.8629,
      "bnb": -31.16935,
      "brl": -10.72899,
      "btc": -17.92527,
      "cad": -9.69836,
      "chf": -11.72926,
      "clp": -8.73554,
      "cny": -10.80828,
      "czk": -12.91209,
      "dkk": -11.64921,
      "dot": -16.91946,
      "eos": -7.17541,
      "eth": -46.10638,
      "eur": -11.7135,
      "gbp": -10.72673,
      "gel": -11.68218,
      "hkd": -11.36645,
      "huf": -13.76104,
      "idr": -11.47716,
      "ils": -13.43316,
      "inr": -10.38181,
      "jpy": -9.43547,
      "krw": -8.77601,
      "kwd": -11.01453,
      "lkr": -10.45159,
      "ltc": -33.67952,
      "mmk": -10.82041,
      "mxn": -11.77259,
      "myr": -11.42858,
      "ngn": -11.66194,
      "nok": -8.26865,
      "nzd": -8.23386,
      "php": -10.82707,
      "pkr": -10.97767,
      "pln": -12.20532,
      "rub": -7.69811,
      "sar": -10.8611,
      "sek": -10.90734,
      "sgd": -10.74594,
      "sol": -28.05917,
      "thb": -11.45402,
      "try": -8.05048,
      "twd": -8.42571,
      "uah": -11.56709,
      "usd": -10.8629,
      "vef": -10.8629,
      "vnd": -10.1822,
      "xag": -14.21389,
      "xau": -9.95139,
      "xdr": -12.39626,
      "xlm": -44.25891,
      "xrp": -33.55107,
      "yfi": -17.76751,
      "zar": -12.32896,
      "bits": -17.92527,
      "link": -52.51456,
      "sats": -17.92527
    },
    "price_change_percentage_200d_in_currency": {
      "aed": 267.18609,
      "ars": 351.28463,
      "aud": 254.81558,
      "bch": 185.0197,
      "bdt": 266.09764,
      "bhd": 267.22329,
      "bmd": 267.23109,
      "bnb": 198.49222,
      "brl": 245.72965,
      "btc": 231.0708,
      "cad": 250.25197,
      "chf": 225.96943,
      "clp": 259.84404,
      "cny": 267.14422,
      "czk": 217.42145,
      "dkk": 227.15527,
      "dot": 522.96156,
      "eos": 504.92887,
      "eth": 191.27044,
      "eur": 227.04845,
      "gbp": 237.97235,
      "gel": 244.83895,
      "hkd": 267.91384,
      "huf": 215.86103,
      "idr": 265.55606,
      "ils": 248.51035,
      "inr": 268.79854,
      "jpy": 249.19087,
      "krw": 252.48388,
      "kwd": 263.9435,
      "lkr": 271.97742,
      "ltc": 318.33429,
      "mmk": 267.40612,
      "mxn": 234.29284,
      "myr": 248.47798,
      "ngn": 264.61972,
      "nok": 234.04948,
      "nzd": 255.27921,
      "php": 259.6596,
      "pkr": 272.80778,
      "pln": 229.8891,
      "rub": 200.94153,
      "sar": 267.42622,
      "sek": 218.10241,
      "sgd": 247.89687,
      "sol": 372.83868,
      "thb": 254.05939,
      "try": 320.76293,
      "twd": 237.26015,
      "uah": 264.59556,
      "usd": 267.23109,
      "vef": 267.23109,
      "vnd": 285.57967,
      "xag": 209.11552,
      "xau": 209.65019,
      "xdr": 235.01356,
      "xlm": 286.59884,
      "xrp": 287.31274,
      "yfi": 381.82934,
      "zar": 248.28147,
      "bits": 231.0708,
      "link": 286.71115,
      "sats": 231.0708
    },
    "price_change_percentage_1y_in_currency": {
      "aed": 157.56702,
      "ars": 252.70762,
      "aud": 168.71565,
      "bch": 59.37056,
      "bdt": 163.47305,
      "bhd": 157.67577,
      "bmd": 157.60195,
      "bnb": 75.27275,
      "brl": 162.0254,
      "btc": 37.26337,
      "cad": 162.00172,
      "chf": 141.63783,
      "clp": 168.06656,
      "cny": 159.35986,
      "czk": 138.5718,
      "dkk": 145.36237,
      "dot": 213.29991,
      "eos": 161.4024,
      "eth": 63.8862,
      "eur": 145.28556,
      "gbp": 148.18634,
      "gel": 158.08076,
      "hkd": 158.10423,
      "huf": 144.85424,
      "idr": 170.46617,
      "ils": 135.0842,
      "inr": 167.42055,
      "jpy": 158.69915,
      "krw": 170.00114,
      "kwd": 157.63649,
      "lkr": 161.20417,
      "ltc": 50.46994,
      "mmk": 157.72473,
      "mxn": 159.58398,
      "myr": 148.97399,
      "ngn": 147.44461,
      "nok": 151.08334,
      "nzd": 170.30952,
      "php": 160.37558,
      "pkr": 162.98094,
      "pln": 144.41436,
      "rub": 131.20792,
      "sar": 157.62151,
      "sek": 139.94294,
      "sgd": 152.96557,
      "sol": 108.00373,
      "thb": 144.28635,
      "try": 211.91529,
      "twd": 144.18275,
      "uah": 158.72508,
      "usd": 157.60195,
      "vef": 157.60195,
      "vnd": 171.62625,
      "xag": 102.71558,
      "xau": 94.0354,
      "xdr": 140.1676,
      "xlm": -36.77404,
      "xrp": -45.97408,
      "yfi": 140.27727,
      "zar": 157.25483,
      "bits": 37.26337,
      "link": 9.43172,
      "sats": 37.26337
    },
    "market_cap_change_24h_in_currency": {
      "aed": -38471144.06770846,
      "ars": -13542506086.725441,
      "aud": -16140316.76149024,
      "bch": -18424.555036447324,
      "bdt": -1272282902.385156,
      "bhd": -3949056.0355132245,
      "bmd": -10475464.688280039,
      "bnb": -12327.79333604334,
      "brl": -56938870.54130589,
      "btc": -90.6621296091394,
      "cad": -14465031.381724479,
      "chf": -8455506.848307285,
      "clp": -10100197435.574907,
      "cny": -75233920.38261317,
      "czk": -219787499.52678266,
      "dkk": -67046563.877662666,
      "dot": -2724473.901428079,
      "eos": -21249483.516472075,
      "eth": -2468.760163610051,
      "eur": -8982955.601251267,
      "gbp": -7756061.293873446,
      "gel": -28177601.610482793,
      "hkd": -81638880.41362458,
      "huf": -3550183976.011344,
      "idr": -170046407888.01743,
      "ils": -35415091.29019943,
      "inr": -914590320.2181902,
      "jpy": -1547904839.5745292,
      "krw": -14549913595.141808,
      "kwd": -3202047.979087352,
      "lkr": -3152522655.868549,
      "ltc": -89459.19554910524,
      "mmk": -21988000380.699806,
      "mxn": -196837391.26964593,
      "myr": -44268894.25237431,
      "ngn": -16057281984.096668,
      "nok": -106915214.4422206,
      "nzd": -17670510.530476306,
      "php": -598014299.7103012,
      "pkr": -2953784839.229803,
      "pln": -38146471.88814893,
      "rub": -843176144.3811154,
      "sar": -39309377.32741513,
      "sek": -100257636.58523157,
      "sgd": -13449153.342670416,
      "sol": -58169.573048402905,
      "thb": -340427710.83147013,
      "try": -428258320.37807256,
      "twd": -315217313.1478563,
      "uah": -431783599.24393123,
      "usd": -10475464.688280039,
      "vef": -1048908.2792374808,
      "vnd": -275479201236.0702,
      "xag": -276064.13754655985,
      "xau": -3137.9849514798475,
      "xdr": -7302708.320817226,
      "xlm": -25621010.23136804,
      "xrp": -3480089.2675752454,
      "yfi": -1913.2463592151864,
      "zar": -184851932.87024817,
      "bits": -90662129.60913938,
      "link": -434293.39807947073,
      "sats": -9066212960.913939
    },
    "market_cap_change_percentage_24h_in_currency": {
      "aed": -97.39957,
      "ars": -97.40207,
      "aud": -97.38183,
      "bch": -97.32786,
      "bdt": -97.39814,
      "bhd": -97.39943,
      "bmd": -97.39957,
      "bnb": -97.35592,
      "brl": -97.37,
      "btc": -97.35625,
      "cad": -97.38819,
      "chf": -97.39589,
      "clp": -97.40124,
      "cny": -97.39845,
      "czk": -97.39478,
      "dkk": -97.39346,
      "dot": -97.35729,
      "eos": -97.37565,
      "eth": -97.3537,
      "eur": -97.39382,
      "gbp": -97.39373,
      "gel": -97.39473,
      "hkd": -97.39478,
      "huf": -97.40272,
      "idr": -97.39217,
      "ils": -97.39138,
      "inr": -97.40665,
      "jpy": -97.40262,
      "krw": -97.38069,
      "kwd": -97.399,
      "lkr": -97.39276,
      "ltc": -97.33626,
      "mmk": -97.39957,
      "mxn": -97.39452,
      "myr": -97.39865,
      "ngn": -97.39682,
      "nok": -97.37715,
      "nzd": -97.35654,
      "php": -97.39383,
      "pkr": -97.3898,
      "pln": -97.39161,
      "rub": -97.39062,
      "sar": -97.39954,
      "sek": -97.38855,
      "sgd": -97.39568,
      "sol": -97.40909,
      "thb": -97.39245,
      "try": -97.39823,
      "twd": -97.38504,
      "uah": -97.38906,
      "usd": -97.39957,
      "vef": -97.39957,
      "vnd": -97.39614,
      "xag": -97.35011,
      "xau": -97.38516,
      "xdr": -97.39957,
      "xlm": -97.33121,
      "xrp": -97.30107,
      "yfi": -97.38768,
      "zar": -97.39079,
      "bits": -97.35625,
      "link": -97.43148,
      "sats": -97.35625
    },
    "total_supply": 17070481.49032999,
    "max_supply": null,
    "max_supply_infinite": false,
    "circulating_supply": 17070481.49032999,
    "last_updated": "2025-08-20T05:00:56.626Z"
  },
  "community_data": {
    "facebook_likes": null,
    "reddit_average_posts_48h": 0.0,
    "reddit_average_comments_48h": 0.0,
    "reddit_subscribers": 0,
    "reddit_accounts_active_48h": 0,
    "telegram_channel_user_count": 5366
  },
  "developer_data": {
    "forks": 0,
    "stars": 0,
    "subscribers": 0,
    "total_issues": 0,
    "closed_issues": 0,
    "pull_requests_merged": 0,
    "pull_request_contributors": 0,
    "code_additions_deletions_4_weeks": {
      "additions": null,
      "deletions": null
    },
    "commit_count_4_weeks": 0,
    "last_4_weeks_commit_activity_series": []
  },
  "status_updates": [],
  "last_updated": "2025-08-20T05:00:56.626Z",
  "tickers": [
    {
      "base": "0X1D6CBDC6B29C6AFBAE65444A1F65BA9252B8CA83",
      "target": "0XE9E7CEA3DEDCA5984780BAFC599BD69ADD087D56",
      "market": {
        "name": "ApeSwap",
        "identifier": "apeswap_bsc",
        "has_trading_incentive": false
      },
      "last": 0.01638261514,
      "volume": 1383.5476072735,
      "converted_last": {
        "btc": 1.44036e-07,
        "eth": 3.92e-06,
        "usd": 0.01636049
      },
      "converted_volume": {
        "btc": 0.00019974,
        "eth": 0.00544205,
        "usd": 22.69
      },
      "trust_score": "red",
      "bid_ask_spread_percentage": 0.617762,
      "timestamp": "2025-08-20T00:24:16+00:00",
      "last_traded_at": "2025-08-20T00:24:16+00:00",
      "last_fetch_at": "2025-08-20T04:58:55+00:00",
      "is_anomaly": false,
      "is_stale": false,
      "trade_url": "https://apeswap.finance/swap?inputCurrency=0x1d6cbdc6b29c6afbae65444a1f65ba9252b8ca83&outputCurrency=0xe9e7cea3dedca5984780bafc599bd69add087d56",
      "token_info_url": null,
      "coin_id": "tor",
      "target_coin_id": "binance-peg-busd",
      "coin_mcap_usd": 279680.1981046212
    },
    {
      "base": "0X74E23DF9110AA9EA0B6FF2FAEE01E740CA1C642E",
      "target": "0X21BE370D5312F44CB42CE377BC9B8A0CEF1A4C83",
      "market": {
        "name": "SpookySwap",
        "identifier": "spookyswap",
        "has_trading_incentive": false
      },
      "last": 0.006497026424,
      "volume": 3758.7590250392,
      "converted_last": {
        "btc": 1.7572e-08,
        "eth": 4.78773e-07,
        "usd": 0.00199654
      },
      "converted_volume": {
        "btc": 6.62e-05,
        "eth": 0.00180376,
        "usd": 7.52
      },
      "trust_score": "red",
      "bid_ask_spread_percentage": 0.683335,
      "timestamp": "2025-08-20T05:01:16+00:00",
      "last_traded_at": "2025-08-20T05:01:16+00:00",
      "last_fetch_at": "2025-08-20T05:01:16+00:00",
      "is_anomaly": false,
      "is_stale": false,
      "trade_url": "https://spooky.fi/#/swap?inputCurrency=0x74e23df9110aa9ea0b6ff2faee01e740ca1c642e&outputCurrency=0x21be370d5312f44cb42ce377bc9b8a0cef1a4c83",
      "token_info_url": "https://info.spookyswap.finance/token/0x74e23df9110aa9ea0b6ff2faee01e740ca1c642e",
      "coin_id": "tor",
      "target_coin_id": "wrapped-fantom",
      "coin_mcap_usd": 279680.1981046212
    }
  ]
}